Products.PluginRegistry-2.0-py3.11-nspkg.pth
Products/PluginRegistry/PluginRegistry.py
Products/PluginRegistry/__init__.py
Products/PluginRegistry/configure.zcml
Products/PluginRegistry/exportimport.py
Products/PluginRegistry/interfaces.py
Products/PluginRegistry/tests/__init__.py
Products/PluginRegistry/tests/test_PluginRegistry.py
Products/PluginRegistry/tests/test_exportimport.py
Products/PluginRegistry/www/PluginRegistry.png
Products/PluginRegistry/www/active_plugins.zpt
Products/PluginRegistry/www/arrow-down.gif
Products/PluginRegistry/www/arrow-left.gif
Products/PluginRegistry/www/arrow-right.gif
Products/PluginRegistry/www/arrow-up.gif
Products/PluginRegistry/www/export_import.zpt
Products/PluginRegistry/www/plugins.zpt
Products/PluginRegistry/www/two_lists.zpt
Products/PluginRegistry/xml/pirExport.xml
Products.PluginRegistry-2.0.dist-info/LICENSE.txt
Products.PluginRegistry-2.0.dist-info/METADATA
Products.PluginRegistry-2.0.dist-info/WHEEL
Products.PluginRegistry-2.0.dist-info/entry_points.txt
Products.PluginRegistry-2.0.dist-info/namespace_packages.txt
Products.PluginRegistry-2.0.dist-info/top_level.txt
Products.PluginRegistry-2.0.dist-info/RECORD
